constrained_opt_mcp/__init__.py
constrained_opt_mcp/core/__init__.py
constrained_opt_mcp/core/base_models.py
constrained_opt_mcp/core/problem_types.py
constrained_opt_mcp/examples/financial/__init__.py
constrained_opt_mcp/examples/financial/portfolio_optimization.py
constrained_opt_mcp/examples/financial/risk_management.py
constrained_opt_mcp/models/__init__.py
constrained_opt_mcp/models/cvxpy_models.py
constrained_opt_mcp/models/highs_models.py
constrained_opt_mcp/models/ortools_models.py
constrained_opt_mcp/models/z3_models.py
constrained_opt_mcp/server/__init__.py
constrained_opt_mcp/server/main.py
constrained_opt_mcp/solvers/__init__.py
constrained_opt_mcp/solvers/cvxpy_solver.py
constrained_opt_mcp/solvers/highs_solver.py
constrained_opt_mcp/solvers/ortools_solver.py
constrained_opt_mcp/solvers/z3_solver.py
constrained_opt_mcp-1.0.1.dist-info/METADATA
constrained_opt_mcp-1.0.1.dist-info/WHEEL
constrained_opt_mcp-1.0.1.dist-info/entry_points.txt
constrained_opt_mcp-1.0.1.dist-info/licenses/LICENSE
constrained_opt_mcp-1.0.1.dist-info/RECORD
