Metadata-Version: 2.4
Name: constrained-opt-mcp
Version: 1.0.1
Summary: General Purpose MCP Server for Constrained Optimization - AI agents for optimization tasks such as portfolio optimization, scheduling, and combinatorial problems
Author-email: Rajnish Sharma <rajnish.sst1@gmail.com>
License: Apache-2.0
License-File: LICENSE
Keywords: ai-agents,combinatorial-optimization,constraint-satisfaction,financial-optimization,linear-programming,mathematical-optimization,mcp,model-context-protocol,operations-research,optimization,portfolio-optimization,scheduling
Classifier: Development Status :: 4 - Beta
Classifier: Framework :: Jupyter
Classifier: Intended Audience :: Developers
Classifier: Intended Audience :: Financial and Insurance Industry
Classifier: Intended Audience :: Science/Research
Classifier: License :: OSI Approved :: Apache Software License
Classifier: Operating System :: OS Independent
Classifier: Programming Language :: Python :: 3
Classifier: Programming Language :: Python :: 3.10
Classifier: Programming Language :: Python :: 3.11
Classifier: Programming Language :: Python :: 3.12
Classifier: Topic :: Office/Business :: Financial :: Investment
Classifier: Topic :: Scientific/Engineering :: Artificial Intelligence
Classifier: Topic :: Scientific/Engineering :: Mathematics
Classifier: Topic :: Software Development :: Libraries :: Python Modules
Classifier: Topic :: System :: Distributed Computing
Requires-Python: >=3.10
Requires-Dist: cvxpy>=1.6.0
Requires-Dist: fastmcp>=0.1.0
Requires-Dist: highspy>=1.11.0
Requires-Dist: ipywidgets>=8.0.0
Requires-Dist: jupyter>=1.0.0
Requires-Dist: matplotlib>=3.7.0
Requires-Dist: numpy>=1.24.0
Requires-Dist: ortools<9.15.0
Requires-Dist: pandas>=2.0.0
Requires-Dist: pydantic>=2.0.0
Requires-Dist: returns>=0.20.0
Requires-Dist: scipy>=1.10.0
Requires-Dist: seaborn>=0.12.0
Requires-Dist: z3-solver>=4.14.1.0
